jsonschema_lint/__init__.py
jsonschema_lint/_cli/__init__.py
jsonschema_lint/_cli/constants.py
jsonschema_lint/_cli/main.py
jsonschema_lint/_cli/resolver.py
jsonschema_lint/_cli/rule_loader.py
jsonschema_lint/_cli/schema_loader.py
jsonschema_lint/compat.py
jsonschema_lint/json_ast/__init__.py
jsonschema_lint/json_ast/errors.py
jsonschema_lint/json_ast/location.py
jsonschema_lint/json_ast/nodes.py
jsonschema_lint/json_ast/parser.py
jsonschema_lint/json_ast/tokenizer.py
jsonschema_lint/linter.py
jsonschema_lint/py.typed
jsonschema_lint/utils.py
jsonschema_lint/yaml_ast/__init__.py
jsonschema_lint/yaml_ast/errors.py
jsonschema_lint/yaml_ast/parser.py
jsonschema_lint/yaml_ast/utils.py
jsonschema_lint-0.1.0.dist-info/entry_points.txt
jsonschema_lint-0.1.0.dist-info/LICENSE.txt
jsonschema_lint-0.1.0.dist-info/WHEEL
jsonschema_lint-0.1.0.dist-info/METADATA
jsonschema_lint-0.1.0.dist-info/RECORD
