Metadata-Version: 2.1
Name: jsonschema-lint
Version: 0.1.0
Summary: Linter for JSON Schema instances.
Home-page: https://github.com/jacksmith15/jsonschema-lint
Author: Jack Smith
Requires-Python: >=3.8,<4.0
Classifier: Programming Language :: Python :: 3
Classifier: Programming Language :: Python :: 3.10
Classifier: Programming Language :: Python :: 3.8
Classifier: Programming Language :: Python :: 3.9
Provides-Extra: yaml
Requires-Dist: PyYAML (>=6.0,<7.0); extra == "yaml"
Requires-Dist: click (>=8.0.3,<9.0.0)
Requires-Dist: jsonschema (>=4.2.1,<5.0.0)
Project-URL: Repository, https://github.com/jacksmith15/jsonschema-lint
